bussinwebx_get/__init__.py
bussinwebx_get-2.0.1.dist-info/LICENSE
bussinwebx_get-2.0.1.dist-info/METADATA
bussinwebx_get-2.0.1.dist-info/WHEEL
bussinwebx_get-2.0.1.dist-info/top_level.txt
bussinwebx_get-2.0.1.dist-info/RECORD
