Metadata-Version: 2.1
Name: bussinwebx_get
Version: 2.0.1
Summary: Be able to make GET requests to buss:// websites and get IPs for buss:// websites.
Maintainer: The Odd Cell
License: MIT License
Project-URL: Repository, https://github.com/TheOddCell/bussinwebx-get.git
Project-URL: Issues, https://github.com/TheOddCell/bussinwebx-get/issues
Keywords: webx,buss,facedev
Classifier: Development Status :: 5 - Production/Stable
Classifier: Intended Audience :: Developers
Classifier: License :: OSI Approved :: MIT License
Requires-Python: >=3.7
License-File: LICENSE
Requires-Dist: requests
